django_start_api/__init__.py
django_start_api/creator.py
django_start_api/insert.py
django_start_api/start_api.py
django_startapi/__init__.py
django_startapi/creator.py
django_startapi/insert.py
django_startapi/start_api.py
django_startapi-0.0.2.dev2.data/scripts/startapi
django_startapi-0.0.2.dev2.dist-info/LICENSE
django_startapi-0.0.2.dev2.dist-info/METADATA
django_startapi-0.0.2.dev2.dist-info/WHEEL
django_startapi-0.0.2.dev2.dist-info/top_level.txt
django_startapi-0.0.2.dev2.dist-info/RECORD
