Metadata-Version: 2.1
Name: django-startapi
Version: 0.0.2.dev2
Summary: Quick REST API creation
Home-page: https://github.com/stefanobazzi/django_startapi
Author: Stefano Bazzi
Author-email: stefanobazzi@yahoo.it
License: UNKNOWN
Platform: UNKNOWN
Classifier: Programming Language :: Python :: 3
Classifier: License :: OSI Approved :: MIT License
Classifier: Operating System :: OS Independent
Requires-Python: >=3.6
Requires-Dist: Django (>=3.0.3)
Requires-Dist: djangorestframework (>=3.11.0)
Requires-Dist: PyYAML (>=5.3)
